j_basic_stock_prediction/__init__.py
j_basic_stock_prediction/predict_stocks.py
j_basic_stock_prediction/pytransform/__init__.py
j_basic_stock_prediction/pytransform/platforms/darwin/x86_64/_pytransform.dylib
j_basic_stock_prediction/pytransform/platforms/linux/x86_64/_pytransform.so
j_basic_stock_prediction/pytransform/platforms/windows/x86_64/_pytransform.dll
j_basic_stock_prediction-0.0.12.dist-info/LICENSE
j_basic_stock_prediction-0.0.12.dist-info/METADATA
j_basic_stock_prediction-0.0.12.dist-info/WHEEL
j_basic_stock_prediction-0.0.12.dist-info/top_level.txt
j_basic_stock_prediction-0.0.12.dist-info/RECORD
